mewbot/io/rss/__init__.py
mewbot/io/rss/events.py
mewbot_io_rss-0.1.0.dist-info/LICENSE.md
mewbot_io_rss-0.1.0.dist-info/METADATA
mewbot_io_rss-0.1.0.dist-info/WHEEL
mewbot_io_rss-0.1.0.dist-info/top_level.txt
mewbot_io_rss-0.1.0.dist-info/RECORD
