Metadata-Version: 2.1
Name: mewbot-io-rss
Version: 0.1.0
Summary: A plugin which lets mewbot consume RSS feeds.
Home-page: https://github.com/ajCameron/mewbot-io-rss
Author: Alex Cameron
Author-email: mewbot@quicksilver.london
Maintainer: Alex Cameron
Maintainer-email: alex.alexcameron@quicksilver.london
License: {#- source: http://opensource.org/licenses/MIT #}
Project-URL: Bug Tracker, https://github.com/ajCameron/mewbot-rss/issues
Classifier: Development Status :: 4 - Beta
Classifier: Intended Audience :: Developers
Classifier: Programming Language :: Python
Classifier: Programming Language :: Python :: 3.10
Classifier: Programming Language :: Python :: 3.11
Classifier: Programming Language :: Python :: 3.12
Classifier: Programming Language :: Python :: 3 :: Only
Classifier: Programming Language :: Python :: Implementation :: CPython
Classifier: Programming Language :: Python :: Implementation :: PyPy
Classifier: Operating System :: OS Independent
Classifier: License :: OSI Approved :: MIT License
Requires-Python: >=3.10
License-File: LICENSE.md
Requires-Dist: mewbot ~=0.0.3
Requires-Dist: mewbot-api ~=0.0.3
Requires-Dist: mewbot-io ~=0.0.3
Requires-Dist: mewbot-test ~=0.0.3
Requires-Dist: feedparser ~=6.0.10
